MANIFEST.in
README.md
setup.py
entropix/__init__.py
entropix/main.py
entropix.egg-info/PKG-INFO
entropix.egg-info/SOURCES.txt
entropix.egg-info/dependency_links.txt
entropix.egg-info/entry_points.txt
entropix.egg-info/not-zip-safe
entropix.egg-info/requires.txt
entropix.egg-info/top_level.txt
entropix/core/__init__.py
entropix/core/evaluator.py
entropix/core/sampler.py
entropix/exceptions/__init__.py
entropix/exceptions/method.py
entropix/exceptions/parameter.py
entropix/logging/__init__.py
entropix/logging/logging.yml
entropix/utils/__init__.py
entropix/utils/config.py
entropix/utils/data.py
entropix/utils/immutables.py